drf_partial_response/__init__.py
drf_partial_response/constants.py
drf_partial_response/decorators.py
drf_partial_response/serializers.py
drf_partial_response/utils.py
drf_partial_response/views.py
drf_partial_response/__pycache__/__init__.cpython-38.pyc
drf_partial_response/__pycache__/constants.cpython-38.pyc
drf_partial_response/__pycache__/decorators.cpython-38.pyc
drf_partial_response/__pycache__/serializers.cpython-38.pyc
drf_partial_response/__pycache__/utils.cpython-38.pyc
drf_partial_response/__pycache__/views.cpython-38.pyc
drf_partial_response-0.1.5.dist-info/LICENSE
drf_partial_response-0.1.5.dist-info/METADATA
drf_partial_response-0.1.5.dist-info/WHEEL
drf_partial_response-0.1.5.dist-info/top_level.txt
drf_partial_response-0.1.5.dist-info/RECORD
