Metadata-Version: 2.1
Name: drf-partial-response
Version: 0.1.5
Summary: Implements Google's partial response in Django RestFramework (Fork from Zapier's package and upgrade version)
Home-page: https://github.com/thongnguyenhuu/drf-partial-response
Author: Thong Nguyen
Author-email: nguyenthonght@gmail.com
License: BSD
Download-URL: https://github.com/thongnguyenhuu/drf-partial-response/tarball/0.1.5
Platform: UNKNOWN
Classifier: Development Status :: 4 - Beta
Classifier: Environment :: Web Environment
Classifier: Framework :: Django
Classifier: Framework :: Django :: 1.11
Classifier: Framework :: Django :: 2.0
Classifier: Framework :: Django :: 2.1
Classifier: Framework :: Django :: 3.0
Classifier: Intended Audience :: Developers
Classifier: License :: OSI Approved :: BSD License
Classifier: Operating System :: OS Independent
Classifier: Natural Language :: English
Classifier: Programming Language :: Python :: 2
Classifier: Programming Language :: Python :: 2.7
Classifier: Programming Language :: Python :: 3
Classifier: Programming Language :: Python :: 3.5
Classifier: Programming Language :: Python :: 3.6
Classifier: Programming Language :: Python :: 3.7
Classifier: Programming Language :: Python :: 3.8
Classifier: Topic :: Internet :: WWW/HTTP
Classifier: Topic :: Software Development :: Libraries :: Python Modules
Requires-Dist: isort
Requires-Dist: jsonmask
Requires-Dist: Django (>=1.11)
Requires-Dist: djangorestframework (>=3.5)
Requires-Dist: six
Requires-Dist: factory-boy
